convert_case/__init__.py
convert_case/__main__.py
convert_case/camel.py
convert_case/definitions.py
convert_case/exceptions.py
convert_case/kebab.py
convert_case/lower.py
convert_case/pascal.py
convert_case/py.typed
convert_case/sentence.py
convert_case/snake.py
convert_case/title.py
convert_case/upper.py
convert_case-1.2.3.dist-info/LICENSE.md
convert_case-1.2.3.dist-info/METADATA
convert_case-1.2.3.dist-info/WHEEL
convert_case-1.2.3.dist-info/top_level.txt
convert_case-1.2.3.dist-info/RECORD
