Metadata-Version: 2.1
Name: convert-case
Version: 1.2.3
Summary: Convert between string cases with built-in case inference.
Home-page: https://github.com/JoelLefkowitz/convert-case
Author: joellefkowitz
Author-email: joellefkowitz@hotmail.com
License: UNKNOWN
Project-URL: Bug Tracker, https://github.com/JoelLefkowitz/convert-case/issues
Project-URL: CI, https://github.com/JoelLefkowitz/convert-case/actions
Project-URL: Documentation, https://convert-case.readthedocs.io/en/latest/
Project-URL: Source Code, https://github.com/JoelLefkowitz/convert-case
Platform: UNKNOWN
Classifier: Intended Audience :: Developers
Classifier: License :: OSI Approved :: MIT License
Classifier: Operating System :: OS Independent
Classifier: Programming Language :: Python :: 3.6
Classifier: Programming Language :: Python :: 3.7
Classifier: Programming Language :: Python :: 3.8
Classifier: Programming Language :: Python :: 3.9
Classifier: Topic :: Software Development :: Libraries :: Python Modules
Requires-Python: >=3.6
License-File: LICENSE.md
Provides-Extra: all
Requires-Dist: assertpy ; extra == 'all'
Requires-Dist: autoflake ; extra == 'all'
Requires-Dist: bandit ; extra == 'all'
Requires-Dist: black ; extra == 'all'
Requires-Dist: bump2version ; extra == 'all'
Requires-Dist: coverage ; extra == 'all'
Requires-Dist: freezegun ; extra == 'all'
Requires-Dist: isort ; extra == 'all'
Requires-Dist: mock ; extra == 'all'
Requires-Dist: mypy ; extra == 'all'
Requires-Dist: pylint ; extra == 'all'
Requires-Dist: pytest ; extra == 'all'
Requires-Dist: pytest-mocha ; extra == 'all'
Requires-Dist: pytest-sugar ; extra == 'all'
Requires-Dist: quickdocs ; extra == 'all'
Requires-Dist: tox ; extra == 'all'
Requires-Dist: twine ; extra == 'all'
Requires-Dist: wheel ; extra == 'all'
Provides-Extra: formatters
Requires-Dist: autoflake ; extra == 'formatters'
Requires-Dist: black ; extra == 'formatters'
Requires-Dist: isort ; extra == 'formatters'
Provides-Extra: linters
Requires-Dist: bandit ; extra == 'linters'
Requires-Dist: mypy ; extra == 'linters'
Requires-Dist: pylint ; extra == 'linters'
Provides-Extra: release
Requires-Dist: bump2version ; extra == 'release'
Requires-Dist: quickdocs ; extra == 'release'
Requires-Dist: twine ; extra == 'release'
Requires-Dist: wheel ; extra == 'release'
Provides-Extra: tests
Requires-Dist: assertpy ; extra == 'tests'
Requires-Dist: coverage ; extra == 'tests'
Requires-Dist: freezegun ; extra == 'tests'
Requires-Dist: mock ; extra == 'tests'
Requires-Dist: pytest ; extra == 'tests'
Requires-Dist: pytest-mocha ; extra == 'tests'
Requires-Dist: pytest-sugar ; extra == 'tests'
Requires-Dist: tox ; extra == 'tests'
